autoads/__init__.py
autoads/client.py
autoads/gads.py
autoads/keywords.py
autoads/models.py
autoads_test-0.3.4.dist-info/METADATA
autoads_test-0.3.4.dist-info/WHEEL
autoads_test-0.3.4.dist-info/top_level.txt
autoads_test-0.3.4.dist-info/RECORD
